odoo/addons/crm_lost_reason_multi_company/README.rst
odoo/addons/crm_lost_reason_multi_company/__init__.py
odoo/addons/crm_lost_reason_multi_company/__manifest__.py
odoo/addons/crm_lost_reason_multi_company/i18n/crm_lost_reason_multi_company.pot
odoo/addons/crm_lost_reason_multi_company/i18n/it.po
odoo/addons/crm_lost_reason_multi_company/models/__init__.py
odoo/addons/crm_lost_reason_multi_company/models/crm_lead.py
odoo/addons/crm_lost_reason_multi_company/models/crm_lost_reason.py
odoo/addons/crm_lost_reason_multi_company/readme/CONTRIBUTORS.md
odoo/addons/crm_lost_reason_multi_company/readme/DESCRIPTION.md
odoo/addons/crm_lost_reason_multi_company/security/crm_lost_reason.xml
odoo/addons/crm_lost_reason_multi_company/static/description/icon.png
odoo/addons/crm_lost_reason_multi_company/static/description/index.html
odoo/addons/crm_lost_reason_multi_company/views/crm_lost_reason.xml
odoo_addon_crm_lost_reason_multi_company-18.0.1.0.0.2.dist-info/METADATA
odoo_addon_crm_lost_reason_multi_company-18.0.1.0.0.2.dist-info/WHEEL
odoo_addon_crm_lost_reason_multi_company-18.0.1.0.0.2.dist-info/top_level.txt
odoo_addon_crm_lost_reason_multi_company-18.0.1.0.0.2.dist-info/RECORD
